{"stats":{"minecraft:used":{"minecraft:stone_sword":14,"minecraft:stone_pickaxe":10,"minecraft:lime_wool":118,"minecraft:ladder":2,"minecraft:chest":39,"minecraft:wooden_pickaxe":1,"minecraft:white_wool":121,"minecraft:golden_apple":8,"minecraft:dirt":2,"minecraft:anvil":1,"minecraft:light_blue_wool":51,"minecraft:orange_wool":72,"minecraft:shears":34,"minecraft:end_stone":101,"minecraft:obsidian":8,"minecraft:dark_oak_planks":72,"minecraft:diamond_pickaxe":3,"minecraft:firework_rocket":1,"minecraft:red_wool":102,"minecraft:totem_of_undying":2,"minecraft:yellow_wool":83,"minecraft:stone_axe":4,"minecraft:bedrock":2,"minecraft:wooden_sword":56,"minecraft:black_stained_glass":3,"minecraft:lime_stained_glass":56},"minecraft:picked_up":{"minecraft:anvil":1,"minecraft:yellow_wool":24,"minecraft:black_bed":1,"minecraft:bedrock":8,"minecraft:gunpowder":2,"minecraft:wither_skeleton_skull":2,"minecraft:dirt":2,"minecraft:paper":8,"minecraft:bone":2,"minecraft:bow":5,"minecraft:iron_ingot":1865,"minecraft:chest":1,"minecraft:lime_wool":59,"minecraft:end_stone":25,"minecraft:red_wool":1,"minecraft:ink_sac":1,"minecraft:dead_bush":1,"minecraft:leather_helmet":2,"minecraft:orange_wool":4,"minecraft:dark_oak_planks":6,"minecraft:tnt":5,"minecraft:stone_sword":1,"minecraft:lime_dye":1,"minecraft:diamond_chestplate":2,"minecraft:slime_ball":6,"minecraft:diamond":44,"minecraft:beetroot_seeds":5,"minecraft:netherite_helmet":1,"minecraft:golden_apple":8,"minecraft:golden_horse_armor":1,"minecraft:gold_ingot":249,"minecraft:emerald":46,"minecraft:coal":1,"minecraft:cod":3,"minecraft:white_wool":48,"minecraft:diamond_pickaxe":1,"minecraft:ender_pearl":16},"minecraft:killed":{"minecraft:wither_skeleton":1},"minecraft:mined":{"minecraft:dark_oak_planks":2,"minecraft:light_blue_wool":1,"minecraft:orange_wool":4,"minecraft:end_stone":14,"minecraft:lime_stained_glass":3,"minecraft:lime_wool":51,"minecraft:yellow_wool":7,"minecraft:fire":1,"minecraft:white_wool":12},"minecraft:custom":{"minecraft:mob_kills":1,"minecraft:play_one_minute":196829,"minecraft:leave_game":5,"minecraft:time_since_death":20463,"minecraft:climb_one_cm":3294,"minecraft:time_since_rest":20469,"minecraft:damage_absorbed":400,"minecraft:sprint_one_cm":630858,"minecraft:open_enderchest":4,"minecraft:damage_taken":13639,"minecraft:walk_one_cm":137300,"minecraft:drop":19,"minecraft:damage_dealt":1613,"minecraft:damage_dealt_absorbed":120,"minecraft:fly_one_cm":2115654,"minecraft:player_kills":7,"minecraft:open_chest":52,"minecraft:crouch_one_cm":61252,"minecraft:deaths":34,"minecraft:sneak_time":23645,"minecraft:aviate_one_cm":41167,"minecraft:jump":4754,"minecraft:walk_on_water_one_cm":4096,"minecraft:fall_one_cm":364001},"minecraft:killed_by":{"minecraft:player":14},"minecraft:dropped":{"minecraft:iron_ingot":3,"minecraft:stone_sword":1,"minecraft:diamond":3,"minecraft:lime_wool":1,"minecraft:black_bed":1,"minecraft:cod":1,"minecraft:emerald":3,"minecraft:gunpowder":2,"minecraft:diamond_chestplate":1,"minecraft:slime_ball":2,"minecraft:gold_ingot":1}},"DataVersion":2586}